{"aliases": ["VOCALOID PARADISE 13", "ボーパラ13"], "dates": "2018.09.16", "circles": [{"aliases": ["AHSストア"], "pen_names": ["-"], "position": "-,企業出展,-, -", "links": ["https://www.ah-soft.com/"]}, {"aliases": ["AquaProject"], "pen_names": ["藤枝雅紀"], "position": "KAITO×初音ミク,カイミクPARADISE,A-14, A-14", "links": ["https://www.pixiv.net/member.php?id=76719"]}, {"aliases": ["エノ庭"], "pen_names": ["エノニワ"], "position": "KAITO×初音ミク,カイミクPARADISE,A-06, A-06", "links": ["https://www.pixiv.net/member.php?id=1114989"]}, {"aliases": ["MMM＋どグリット"], "pen_names": ["シヅキヒシロ、十夢臣"], "position": "KAITO×初音ミク,カイミクPARADISE,A-16, A-16"}, {"aliases": ["カーネリアンの奏でる夢"], "pen_names": ["翡翠リマ、夏菜みほ"], "position": "KAITO×初音ミク,カイミクPARADISE,A-19, A-19"}, {"aliases": ["カイミクペーパーラリー企画本部"], "pen_names": ["さくらら、遠野蒼、シヅキヒシロ、ひろむ、藤枝雅紀、あまみ"], "position": "KAITO×初音ミク,カイミクPARADISE,A-11,12, A-11,12", "links": ["http://kaimikuppr.yusarabi.net/"]}, {"aliases": ["ごった煮カメレオン"], "pen_names": ["吉川ひびき"], "position": "KAITO×初音ミク,カイミクPARADISE,A-09, A-09", "links": ["http://wbsr315.blog.fc2.com/"]}, {"aliases": ["theatreθ"], "pen_names": ["しぃた"], "position": "KAITO×初音ミク,カイミクPARADISE,A-23, A-23", "links": ["https://www.pixiv.net/member.php?id=1938803"]}, {"aliases": ["翠緑"], "pen_names": ["スイ"], "position": "KAITO×初音ミク,カイミクPARADISE,A-22, A-22", "links": ["https://www.pixiv.net/member.php?id=11645445"]}, {"aliases": ["slowly"], "pen_names": ["遠野蒼"], "position": "KAITO×初音ミク,カイミクPARADISE,A-10, A-10", "links": ["http://slowly.stars.ne.jp/"]}, {"aliases": ["たそがれうさぎ"], "pen_names": ["ひろむ"], "position": "KAITO×初音ミク,カイミクPARADISE,A-13, A-13", "links": ["http://yusarabi.net/"]}, {"aliases": ["twinkledisc"], "pen_names": ["Dios/シグナルP"], "position": "初音ミク、KAITO,カイミクPARADISE,A-01, A-01", "links": ["https://twinkledisc.net"]}, {"aliases": ["桃源郷"], "pen_names": ["ゆうなぎいく"], "position": "KAITO、初音ミク,カイミクPARADISE,A-02, A-02", "links": ["https://twitter.com/yuunagiiku"]}, {"aliases": ["七色DUET"], "pen_names": ["空汰、凛丸"], "position": "KAITO×初音ミク,カイミクPARADISE,A-03,04, A-03,04", "links": ["http://nanairoduet.blog.fc2.com/"]}, {"aliases": ["nanamix＆sep.off"], "pen_names": ["あまみ、さくらら"], "position": "KAITO×初音ミク,カイミクPARADISE,A-15, A-15", "links": ["https://twitter.com/sepkm"]}, {"aliases": ["ねぎあいすふぁいぶ"], "pen_names": ["すぎ あいね、晟玉"], "position": "KAITO×初音ミク,カイミクPARADISE,A-20, A-20", "links": ["https://www.pixiv.net/member.php?id=12206356"]}, {"aliases": ["風鈴火山"], "pen_names": ["鈴"], "position": "KAITO×初音ミク,カイミクPARADISE,A-21, A-21"}, {"aliases": ["ペーちろ"], "pen_names": ["ペーちろ"], "position": "KAITO×初音ミク,カイミクPARADISE,A-05, A-05", "links": ["https://www.pixiv.net/member.php?id=23114581"]}, {"aliases": ["veil."], "pen_names": ["桃之介、神流"], "position": "KAITO×初音ミク,カイミクPARADISE,A-17,18, A-17,18", "links": ["https://twitter.com/veilxxx"]}, {"aliases": ["マメトコメ"], "pen_names": ["みそ、みりん、きなこ"], "position": "KAITO×初音ミク,カイミクPARADISE,A-07,08, A-07,08", "links": ["https://twitter.com/miso23so"]}, {"aliases": ["青髭海賊団"], "pen_names": ["青髭P"], "position": "巡音ルカ,VOCALOID PARADISE 13,C-23, C-23"}, {"aliases": ["雨霧ノ庵"], "pen_names": ["月代"], "position": "初音ミク,VOCALOID PARADISE 13,D-01, D-01", "links": ["https://twitter.com/saika_tsukisiro"]}, {"aliases": ["alfalfa"], "pen_names": ["ヒナギ、ユウェル"], "position": "初音ミク,VOCALOID PARADISE 13,D-37,38, D-37,38", "links": ["https://www.pixiv.net/member.php?id=606903"]}, {"aliases": ["WallStudio"], "pen_names": ["うｐﾊｼ"], "position": "v flower、ﾀｶﾊｼ,VOCALOID PARADISE 13,D-19, D-19", "links": ["https://wallstudio.hateblo.jp/"]}, {"aliases": ["渦箱"], "pen_names": ["anmo"], "position": "初音ミク,VOCALOID PARADISE 13,D-06, D-06", "links": ["https://twitter.com/n_anmo"]}, {"aliases": ["aledanju"], "pen_names": ["つのみ"], "position": "初音ミク,VOCALOID PARADISE 13,D-04, D-04", "links": ["https://www.pixiv.net/member.php?id=3628088"]}, {"aliases": ["S-Canvas"], "pen_names": ["月灯ゆら、(飲み会芸人P)"], "position": "初音ミク,VOCALOID PARADISE 13,B-04, B-04", "links": ["https://s-canvas.wixsite.com/s-canvas"]}, {"aliases": ["EHAMIC"], "pen_names": ["エハミック"], "position": "鏡音リン・レン、初音ミク、結月ゆかり,VOCALOID PARADISE 13,C-19, C-19", "links": ["http://EHAMIC.com"]}, {"aliases": ["大江戸宅急便"], "pen_names": ["しまむらさん／鼻炎P"], "position": "初音ミク,VOCALOID PARADISE 13,D-30, D-30", "links": ["http://www.ooedo.jp"]}, {"aliases": ["かいりきベア"], "pen_names": ["かいりきベア"], "position": "初音ミク,VOCALOID PARADISE 13,B-03, B-03", "links": ["https://www.youtube.com/user/kairikibear"]}, {"aliases": ["火神堂"], "pen_names": ["火神レオ"], "position": "雪ミク,VOCALOID PARADISE 13,D-36, D-36"}, {"aliases": ["【仮受付】かがみね茶"], "pen_names": ["半月、yoku"], "position": "鏡音リン・レン,VOCALOID PARADISE 13,D-26, D-26", "links": ["http://kagamine-cha.jp/"]}, {"aliases": ["かよぴぃ＆あぷ"], "pen_names": ["かよぴぃ・あぷ"], "position": "GUMI,VOCALOID PARADISE 13,C-31, C-31", "links": ["http://www.nicovideo.jp/mylist/43986353"]}, {"aliases": ["鴉’s reverie \n\tphotography"], "pen_names": ["クシ"], "position": "初音ミク,VOCALOID PARADISE 13,B-12, B-12", "links": ["https://twitter.com/ryo69153067"]}, {"aliases": ["完全1度。"], "pen_names": ["ただすけ"], "position": "神威がくぽ×巡音ルカ,VOCALOID PARADISE 13,D-16, D-16", "links": ["http://uniloid.blog4.fc2.com"]}, {"aliases": ["kirakiと"], "pen_names": ["あむろさん"], "position": "初音ミク（みくずきん）,VOCALOID PARADISE 13,D-05, D-05", "links": ["https://twitter.com/amuro1111"]}, {"aliases": ["ギンユーシジン"], "pen_names": ["冴戒椎也"], "position": "鏡音リン・レン,VOCALOID PARADISE 13,C-17, C-17", "links": ["https://ameblo.jp/shiiyasakai/"]}, {"aliases": ["くるみるく"], "pen_names": ["medyum"], "position": "初音ミク,VOCALOID PARADISE 13,D-03, D-03", "links": ["https://twitter.com/medyum_medyum"]}, {"aliases": ["CROCEVIA"], "pen_names": ["Kazuna"], "position": "初音ミク,VOCALOID PARADISE 13,D-11, D-11", "links": ["https://kazzzuna.tumblr.com/"]}, {"aliases": ["氷ノ月"], "pen_names": ["はるか"], "position": "オールキャラクター,VOCALOID PARADISE 13,D-33,34, D-33,34", "links": ["http://blog.livedoor.jp/kori_no_tsuki/"]}, {"aliases": ["こころり屋"], "pen_names": ["こころりP（オカザキ）"], "position": "初音ミク中心オールキャラ,VOCALOID PARADISE 13,D-10, D-10", "links": ["https://www.pixiv.net/member.php?id=4379384"]}, {"aliases": ["小夏日和"], "pen_names": ["ナナツナツ、京橋 ひよわ"], "position": "初音ミク etc,VOCALOID PARADISE 13,B-09,10, B-09,10"}, {"aliases": ["コロコロうどん"], "pen_names": ["ののこ"], "position": "初音ミク,VOCALOID PARADISE 13,D-21,22, D-21,22", "links": ["https://www.pixiv.net/member.php?id=2458"]}, {"aliases": ["G.Roop \n\t-黒瓜丿美の部屋-"], "pen_names": ["黒瓜丿美"], "position": "IA×kokone、初音ミク×結月ゆかり,VOCALOID PARADISE 13,C-35, C-35", "links": ["https://amycrowley02.wixsite.com/groop"]}, {"aliases": ["終末の呼び声"], "pen_names": ["Kagishiro"], "position": "KAITO,VOCALOID PARADISE 13,C-25, C-25", "links": ["http://kagishiro.nobody.jp/"]}, {"aliases": ["出張　いこいの場"], "pen_names": ["大佐"], "position": "初音ミク,VOCALOID PARADISE 13,C-11, C-11", "links": ["https://twitter.com/aogiri_818"]}, {"aliases": ["シライソト"], "pen_names": ["シライソト"], "position": "IA,VOCALOID PARADISE 13,C-37, C-37", "links": ["http://shiraisoto.wixsite.com/shiraisoto-music"]}, {"aliases": ["Sincerely \n\tSyncopation"], "pen_names": ["ねこぜなおとこ"], "position": "初音ミク、GUMI、CUL,VOCALOID PARADISE 13,C-15, C-15", "links": ["https://twitter.com/697nekoze"]}, {"aliases": ["翠々丼"], "pen_names": ["しばうなな"], "position": "鏡音リン,VOCALOID PARADISE 13,D-14, D-14"}, {"aliases": ["スウィートスウィートmomo通信"], "pen_names": ["momo-nP"], "position": "初音ミク,VOCALOID PARADISE 13,C-09, C-09", "links": ["http://www.nicovideo.jp/mylist/60626918"]}, {"aliases": ["STYLE \n\tof SPIRIT"], "pen_names": ["望夢ん"], "position": "初音ミク,VOCALOID PARADISE 13,D-12, D-12", "links": ["https://twitter.com/nozomun_SHBVD"]}, {"aliases": ["Stripeless"], "pen_names": ["しま"], "position": "初音ミク,VOCALOID PARADISE 13,B-11, B-11", "links": ["http://stripelesslabel.com/"]}, {"aliases": ["Small Rabbit"], "pen_names": ["KoNaMi"], "position": "初音ミク,VOCALOID PARADISE 13,C-07,08, C-07,08", "links": ["https://www.youtube.com/channel/UCef88u5eRi70do-ql3a8Jdw"]}, {"aliases": ["スワ停前"], "pen_names": ["スワテイ（suwa）"], "position": "ボカロ亜種中心オールキャラ,VOCALOID PARADISE 13,D-09, D-09", "links": ["https://www.pixiv.net/member.php?id=202780"]}, {"aliases": ["XM \n\t-Xenon Maiden-"], "pen_names": ["キセノンP"], "position": "初音ミク,VOCALOID PARADISE 13,B-01, B-01", "links": ["http://www.xenonmaiden.com/"]}, {"aliases": ["(たか)はっぴーで愉快な仲間たち"], "pen_names": ["たかはっP"], "position": "初音ミク,VOCALOID PARADISE 13,B-05, B-05", "links": ["http://takahappyp.wixsite.com/takahappy"]}, {"aliases": ["WM"], "pen_names": ["wogura"], "position": "初音ミク,VOCALOID PARADISE 13,D-20, D-20", "links": ["https://www.wogura.com/"]}, {"aliases": ["チェビフェス準備会"], "pen_names": ["aqumin"], "position": "さとうささら,VOCALOID PARADISE 13,D-23,24, D-23,24", "links": ["https://www.cevio-festa.com/"]}, {"aliases": ["childeyes"], "pen_names": ["境ヶ原まるこ"], "position": "初音ミク,VOCALOID PARADISE 13,D-29, D-29", "links": ["https://www.pixiv.net/member.php?id=650344"]}, {"aliases": ["電泳キャラバン"], "pen_names": ["五日P"], "position": "鏡音リン,VOCALOID PARADISE 13,D-15, D-15", "links": ["http://natsukazeholon25.wixsite.com/cometdiver"]}, {"aliases": ["飛梅レコーズ"], "pen_names": ["らしゅりー、舞姫立夏、ヲタ乙、えんぶりょー、切身魚"], "position": "初音ミク、巡音ルカ、結月ゆかり、Sachiko \n\tほか,VOCALOID PARADISE 13,C-03,04, C-03,04", "links": ["http://tobiumerec.tumblr.com/"]}, {"aliases": ["トライアウト（仮）"], "pen_names": ["タカイ"], "position": "初音ミク,VOCALOID PARADISE 13,C-12, C-12", "links": ["https://twitter.com/takai513"]}, {"aliases": ["TreatHunters＆花氷キャメリア"], "pen_names": ["ハロウィンP、夜見しのぶ"], "position": "結月ゆかり、(GUMI、MAYU、鏡音リン、OИE、初音ミク、紲星あかり、v flower),VOCALOID PARADISE 13,C-26, C-26", "links": ["https://twitter.com/jirai_bugtsune"]}, {"aliases": ["TORICOTOR"], "pen_names": ["ぼを"], "position": "初音ミク,VOCALOID PARADISE 13,B-08, B-08", "links": ["http://toricotor.web.fc2.com/"]}, {"aliases": ["Trick \n\t& Treat !"], "pen_names": ["りんね、れんと"], "position": "鏡音リン・レン,VOCALOID PARADISE 13,D-27, D-27", "links": ["https://www.pixiv.net/member.php?id=16443927"]}, {"aliases": ["NAI_IAN"], "pen_names": ["Nai"], "position": "Oliver、結月ゆかり,VOCALOID PARADISE 13,D-18, D-18", "links": ["http://nai6767594.wix.com/lapin"]}, {"aliases": ["生ぐーみん。"], "pen_names": ["メグカップP"], "position": "GUMI（メグッポイド）,VOCALOID PARADISE 13,C-29,30, C-29,30", "links": ["http://www.shin-asakawa.jp/vocaloid/nama_gumin/"]}, {"aliases": ["にぼしのくに"], "pen_names": ["煮干P"], "position": "初音ミク,VOCALOID PARADISE 13,B-06, B-06"}, {"aliases": ["ねくら光学"], "pen_names": ["とつれんず"], "position": "CUL,VOCALOID PARADISE 13,C-38, C-38", "links": ["http://www.nicovideo.jp/mylist/45859808"]}, {"aliases": ["HEARTLAND"], "pen_names": ["Bernis"], "position": "心華,VOCALOID PARADISE 13,C-39, C-39", "links": ["https://twitter.com/CorBernis"]}, {"aliases": ["ハイドランジア"], "pen_names": ["小紫花"], "position": "GUMI、v_flower、洛天依、kokone　他,VOCALOID PARADISE 13,C-34, C-34", "links": ["http://www.nicovideo.jp/mylist/37296589"]}, {"aliases": ["buzz式"], "pen_names": ["ねじ式、buzzG"], "position": "初音ミク、結月ゆかり,VOCALOID PARADISE 13,C-01,02, C-01,02", "links": ["https://www.nejishiki.com/"]}, {"aliases": ["ＢＡＬＡＮ"], "pen_names": ["balan"], "position": "巡音ルカ,VOCALOID PARADISE 13,C-24, C-24", "links": ["https://twitter.com/tag_balan"]}, {"aliases": ["ひきこもり病棟"], "pen_names": ["こころ、トムヨーダP"], "position": "初音ミク,VOCALOID PARADISE 13,D-35, D-35"}, {"aliases": ["秘密基地屋*"], "pen_names": ["宇宙宇宙宇宙宇宙"], "position": "初音ミク,VOCALOID PARADISE 13,C-10, C-10", "links": ["http://www.nicovideo.jp/mylist/49276972"]}, {"aliases": ["VFG"], "pen_names": ["yahiro"], "position": "初音ミク,VOCALOID PARADISE 13,C-13, C-13"}, {"aliases": ["フラクタル・エフェクト"], "pen_names": ["じゅり朱色"], "position": "結月ゆかりの双子の弟×ONE -ARIA ON \n\tTHE PLANETES-,VOCALOID PARADISE 13,D-17, D-17", "links": ["https://twitter.com/juri_syuiro"]}, {"aliases": ["Black \n\tOrder"], "pen_names": ["aymnworks、闇夢ミケ"], "position": "初音ミク、鏡音リン、IA、Vflower etc,VOCALOID PARADISE 13,C-16, C-16", "links": ["https://black-order-list.jimdo.com"]}, {"aliases": ["ぺこぽこ"], "pen_names": ["成瀬みち"], "position": "オールキャラ,VOCALOID PARADISE 13,D-31,32, D-31,32"}, {"aliases": ["【仮受付】ボカスト準備会"], "pen_names": ["ボカスト準備会"], "position": "指定無し,VOCALOID PARADISE 13,D-25, D-25", "links": ["http://voca-st.com/"]}, {"aliases": ["ぼんど"], "pen_names": ["ぼんど"], "position": "IA,VOCALOID PARADISE 13,C-36, C-36", "links": ["http://www.nicovideo.jp/mylist/61789793"]}, {"aliases": ["マイクロム"], "pen_names": ["なの"], "position": "初音ミク,VOCALOID PARADISE 13,D-02, D-02", "links": ["https://twitter.com/nano_393"]}, {"aliases": ["Mine*-まいん-"], "pen_names": ["和泉屋めぐむ"], "position": "鏡音リン・レン,VOCALOID PARADISE 13,D-28, D-28", "links": ["https://twitter.com/megumu1238"]}, {"aliases": ["「溝端れこーず。」"], "pen_names": ["みーぞ"], "position": "初音ミク,VOCALOID PARADISE 13,C-05, C-05", "links": ["http://www.nicovideo.jp/mylist/25361574"]}, {"aliases": ["みるくかふぇ"], "pen_names": ["みるくかふぇ"], "position": "GUMI,VOCALOID PARADISE 13,C-32, C-32", "links": ["https://milkcafe.website"]}, {"aliases": ["METKOV"], "pen_names": ["METKOV"], "position": "初音ミク,VOCALOID PARADISE 13,B-02, B-02", "links": ["http://www.metkov.net/"]}, {"aliases": ["ももいろ白昼夢"], "pen_names": ["ゆうしゃざこ"], "position": "桃音モモ,VOCALOID PARADISE 13,C-21, C-21", "links": ["http://st-zako.la.coocan.jp/momocompi3/"]}, {"aliases": ["もものかんづめ"], "pen_names": ["七宝ふみ＆ロラン"], "position": "初音ミク,VOCALOID PARADISE 13,D-07,08, D-07,08", "links": ["https://www.pixiv.net/member.php?id=888221"]}, {"aliases": ["休み社"], "pen_names": ["Sagishi"], "position": "さとうささら,VOCALOID PARADISE 13,C-22, C-22", "links": ["https://yasumi-sha.booth.pm/"]}, {"aliases": ["ヤング企画"], "pen_names": ["山羊五条　他"], "position": "初音ミク,VOCALOID PARADISE 13,D-13, D-13", "links": ["http://youngkikaku.hatenablog.com"]}, {"aliases": ["よしかい工房"], "pen_names": ["よしかい"], "position": "GUMI,VOCALOID PARADISE 13,C-33, C-33", "links": ["https://twitter.com/yoshi_kai_1st"]}, {"aliases": ["ライムファクトリー"], "pen_names": ["スだち、真斗"], "position": "鏡音リン・レン、初音ミク,VOCALOID PARADISE 13,D-39, D-39", "links": ["https://www.pixiv.net/member.php?id=181544"]}, {"aliases": ["らもポケット"], "pen_names": ["らも（ポケトレＰ）"], "position": "鏡音リン,VOCALOID PARADISE 13,C-18, C-18", "links": ["https://twitter.com/ramo_rock1"]}, {"aliases": ["lol project"], "pen_names": ["Transient Energy"], "position": "初音ミク,VOCALOID PARADISE 13,B-07, B-07", "links": ["http://lolproject.client.jp/"]}, {"aliases": ["WILD \n\tCOLOR RECORDS"], "pen_names": ["ヘルＰ"], "position": "結月ゆかり、IA \n\tROCKS、GUMI、Lily、MEIKO、鏡音リン,VOCALOID PARADISE 13,C-27,28, C-27,28", "links": ["http://www.nicovideo.jp/mylist/22039871"]}, {"aliases": ["ワカバ・プロダクション"], "pen_names": ["ワカバ"], "position": "初音ミク,VOCALOID PARADISE 13,C-06, C-06", "links": ["http://www.nicovideo.jp/mylist/52056518"]}, {"aliases": ["わん博士の調声実験室"], "pen_names": ["甲楽わん"], "position": "初音ミク、GUMI、ONE,VOCALOID PARADISE 13,C-14, C-14", "links": ["https://ameblo.jp/korakuone/entry-12374832755.html"]}, {"aliases": ["AHO-CROSS"], "pen_names": ["神岡ちろる"], "position": "結月ゆかり、紲星あかり,AHS PARADISE,G-16, G-16", "links": ["https://twitter.com/kami_shun0505"]}, {"aliases": ["あるぱかの園"], "pen_names": ["ぱかこ"], "position": "東北きりたん,AHS PARADISE,F-04, F-04"}, {"aliases": ["あろまここあ"], "pen_names": ["マージ"], "position": "弦巻マキ,AHS PARADISE,F-15, F-15", "links": ["https://twitter.com/aromazi"]}, {"aliases": ["いづも合衆国"], "pen_names": ["独占いづも"], "position": "琴葉茜・葵,AHS PARADISE,G-11, G-11", "links": ["https://twitter.com/kotorimedoa"]}, {"aliases": ["植木鉢005"], "pen_names": ["シャコバ"], "position": "紲星あかり,AHS PARADISE,G-13, G-13", "links": ["https://twitter.com/syakoba3"]}, {"aliases": ["eCHOmulti"], "pen_names": ["アズキヤドネル"], "position": "猫村いろは,AHS PARADISE,E-12, E-12", "links": ["https://echomulti.booth.pm/"]}, {"aliases": ["えびのすみか"], "pen_names": ["こえびゆーた"], "position": "氷山キヨテル,AHS PARADISE,E-02, E-02", "links": ["http://www.nicovideo.jp/mylist/36882832"]}, {"aliases": ["緒久屋"], "pen_names": ["緒方久乃"], "position": "弦巻マキ×結月ゆかり,AHS PARADISE,F-13,14, F-13,14", "links": ["http://kusharee.blog101.fc2.com"]}, {"aliases": ["喫茶、甘珈琲"], "pen_names": ["雪日しるべ"], "position": "紲星あかり,AHS PARADISE,G-15, G-15", "links": ["http://www.pixiv.net/member.php?id=7516208"]}, {"aliases": ["CassiteRite"], "pen_names": ["錫凪せいや"], "position": "ボイスロイド,AHS PARADISE,F-16, F-16", "links": ["https://twitter.com/suzu_nagi_2525"]}, {"aliases": ["くりーぴーくらうりー"], "pen_names": ["橘虫"], "position": "東北きりたん,AHS PARADISE,F-05, F-05", "links": ["https://twitter.com/Kiltuchu"]}, {"aliases": ["幻灯事務所"], "pen_names": ["キウイジャム"], "position": "琴葉茜,AHS PARADISE,F-09, F-09", "links": ["https://www.pixiv.net/member.php?id=16362874"]}, {"aliases": ["Silent-Jadeite*Crown"], "pen_names": ["水無月燐、音無乖"], "position": "AHS製ボカロ＆ボイロ多めのオールキャラ,AHS PARADISE,G-09,10, G-09,10", "links": ["http://ameblo.jp/euphorsthia/"]}, {"aliases": ["ささらすぴん"], "pen_names": ["小金井ささら"], "position": "歌愛ユキ,AHS PARADISE,E-09,10, E-09,10", "links": ["http://kgneissr.com"]}, {"aliases": ["四ラユメ亭"], "pen_names": ["四ラユメ"], "position": "琴葉茜・葵,AHS PARADISE,F-08, F-08", "links": ["https://twitter.com/Shirayume44"]}, {"aliases": ["スズモフ屋"], "pen_names": ["スズモフ"], "position": "琴葉姉妹、ボイスロイド全般,AHS PARADISE,F-12, F-12", "links": ["http://ch.nicovideo.jp/suzumf/blomaga/ar1257970"]}, {"aliases": ["たけのこ。"], "pen_names": ["おみなえし"], "position": "琴葉茜,AHS PARADISE,G-14, G-14", "links": ["https://twitter.com/ominaeshin"]}, {"aliases": ["ちくわパフェ"], "pen_names": ["ハルナル"], "position": "氷山キヨテル,AHS PARADISE,E-03, E-03", "links": ["https://twitter.com/harunaru7474"]}, {"aliases": ["Twin's MEMORY"], "pen_names": ["ナナミル"], "position": "紲星あかり,AHS PARADISE,G-07, G-07"}, {"aliases": ["Daisy \n\tcat"], "pen_names": ["雛猫"], "position": "結月ゆかり、弦巻マキ、紲星あかり、琴葉茜、琴葉葵,AHS PARADISE,G-05,06, G-05,06", "links": ["https://twitter.com/hinanekozero"]}, {"aliases": ["ぬかぼし堂"], "pen_names": ["穣"], "position": "氷山キヨテル,AHS PARADISE,E-05, E-05", "links": ["http://peanutsmino.wixsite.com/nukaboshidou"]}, {"aliases": ["ねこうさ亭"], "pen_names": ["皐月雨"], "position": "結月ゆかり、猫村いろは、結月ゆかりの双子の弟,AHS PARADISE,G-02, G-02", "links": ["https://www.pixiv.net/member.php?id=5507792"]}, {"aliases": ["ねこおばさんのおうち"], "pen_names": ["SUMInoisy"], "position": "氷山キヨテル,AHS PARADISE,E-04, E-04", "links": ["https://www.pixiv.net/member.php?id=2593979"]}, {"aliases": ["はなやなごやか"], "pen_names": ["華若葉"], "position": "紲星あかり　他,AHS PARADISE,G-12, G-12", "links": ["http://hnwkb.nagoya/"]}, {"aliases": ["向日葵が咲く季節に･･･"], "pen_names": ["柚空夏菜"], "position": "琴葉茜・葵,AHS PARADISE,F-07, F-07"}, {"aliases": ["vIwIv"], "pen_names": ["いら"], "position": "琴葉茜、琴葉葵、結月ゆかり,AHS PARADISE,F-10, F-10", "links": ["https://twitter.com/irasist_"]}, {"aliases": ["風車茶屋"], "pen_names": ["Sumii"], "position": "結月ゆかり,AHS PARADISE,G-01, G-01", "links": ["https://www.pixiv.net/member.php?id=1049371"]}, {"aliases": ["星しぐれ"], "pen_names": ["祥樹しぐれ"], "position": "結月ゆかり,AHS PARADISE,G-04, G-04", "links": ["https://twitter.com/shigure_44ki"]}, {"aliases": ["(ｏ'∀'ｏ)（マス）"], "pen_names": ["若葉"], "position": "KAITO、歌愛ユキ、猫村いろは,AHS PARADISE,E-11, E-11", "links": ["http://twitter.com/wakaba_aoi"]}, {"aliases": ["迷い家の屋根裏"], "pen_names": ["しのびぃ〜"], "position": "東北きりたん,AHS PARADISE,F-01, F-01", "links": ["https://twitter.com/sinobili"]}, {"aliases": ["モチもち"], "pen_names": ["しか"], "position": "結月ゆかり×弦巻マキ、琴葉姉妹,AHS PARADISE,F-11, F-11", "links": ["https://twitter.com/kth_kwii"]}, {"aliases": ["もりのあるまち"], "pen_names": ["ゆきは"], "position": "東北きりたん,AHS PARADISE,F-02, F-02", "links": ["http://pixiv.me/yukiha19saya"]}, {"aliases": ["YAKI・ONIGIRI"], "pen_names": ["流離薄"], "position": "東北きりたん、音街ウナ,AHS PARADISE,F-06, F-06", "links": ["https://twitter.com/susukiusu"]}, {"aliases": ["Unites Bonds"], "pen_names": ["三国奏"], "position": "ゆづきず(結月ゆかり、紲星あかり)、結月ゆかりの双子の弟,AHS PARADISE,G-03, G-03", "links": ["https://mikuni-ya.booth.pm/"]}, {"aliases": ["翼臨社"], "pen_names": ["もうり みつこ"], "position": "氷山キヨテル,AHS PARADISE,E-01, E-01", "links": ["https://www.pixiv.net/member.php?id=117817"]}, {"aliases": ["横丁商店街"], "pen_names": ["浅葱紅音"], "position": "氷山キヨテル,AHS PARADISE,E-06, E-06", "links": ["https://twitter.com/Arikaze_cos"]}, {"aliases": ["礫瀬草庵"], "pen_names": ["礫瀬杏珠"], "position": "氷山キヨテル（がくキヨ、なちゅろく、ろくなちゅ）,AHS PARADISE,E-07, E-07", "links": ["http://www.pixiv.net/member.php?id=14421298"]}, {"aliases": ["れたす屋"], "pen_names": ["れたすー"], "position": "東北きりたん,AHS PARADISE,F-03, F-03", "links": ["https://www.pixiv.net/member.php?id=245100"]}, {"aliases": ["雨傘置き場"], "pen_names": ["かさぴー"], "position": "結月ゆかり(その他ボイスロイド),ゆかりPARADISE３,J-05, J-05", "links": ["https://twitter.com/Kasapy_"]}, {"aliases": ["アルミーダの解放"], "pen_names": ["アルミーダ"], "position": "結月ゆかり,ゆかりPARADISE３,H-09, H-09", "links": ["http://www.nicovideo.jp/mylist/56009754"]}, {"aliases": ["игрушка（イグルーシュカ）"], "pen_names": ["ぽな粉"], "position": "結月ゆかり,ゆかりPARADISE３,I-20, I-20", "links": ["https://twitter.com/ponapowder"]}, {"aliases": ["伊藤組"], "pen_names": ["シンヲタ"], "position": "結月ゆかり,ゆかりPARADISE３,I-23, I-23", "links": ["https://www.pixiv.net/member.php?id=5923453"]}, {"aliases": ["【仮受付】うさぎの宴準備会"], "pen_names": ["半月"], "position": "結月ゆかり,ゆかりPARADISE３,H-11, H-11", "links": ["http://usa-uta.com/"]}, {"aliases": ["梅ノ屋"], "pen_names": ["ゆかりて"], "position": "結月ゆかり,ゆかりPARADISE３,J-20, J-20", "links": ["https://twitter.com/yukarite"]}, {"aliases": ["EGZA \n\tRECORDS"], "pen_names": ["なだれ"], "position": "結月ゆかり,ゆかりPARADISE３,H-07, H-07", "links": ["http://www.nicovideo.jp/mylist/57712160"]}, {"aliases": ["えれてぃっく"], "pen_names": ["そらうみれい"], "position": "結月ゆかり、Fukase,ゆかりPARADISE３,H-27,28, H-27,28", "links": ["http://www.pixiv.me/r273ei"]}, {"aliases": ["OPERETTA"], "pen_names": ["白脇ジャック"], "position": "結月ゆかり、結月ゆかりの双子の弟,ゆかりPARADISE３,I-08, I-08", "links": ["https://twitter.com/sirowakijack"]}, {"aliases": ["化学質。"], "pen_names": ["薄井硫酸"], "position": "結月ゆかり、紲星あかり、ゆづきず,ゆかりPARADISE３,I-12, I-12", "links": ["https://twitter.com/usrs"]}, {"aliases": ["革は食べられない"], "pen_names": ["シヨミフ"], "position": "結月ゆかり,ゆかりPARADISE３,J-24, J-24", "links": ["https://twitter.com/shiyomifu2101"]}, {"aliases": ["喜創楽楽"], "pen_names": ["WilL"], "position": "結月ゆかり,ゆかりPARADISE３,H-15,16, H-15,16", "links": ["https://twitter.com/WillHex"]}, {"aliases": ["帰宅部"], "pen_names": ["((ゆう))"], "position": "結月ゆかり,ゆかりPARADISE３,J-04, J-04"}, {"aliases": ["北の雪だるま"], "pen_names": ["北彩あい"], "position": "結月ゆかり,ゆかりPARADISE３,J-17, J-17", "links": ["http://snowmannorth.strikingly.com/"]}, {"aliases": ["キマシタワーProduction"], "pen_names": ["キマシタワーP"], "position": "結月ゆかり＆IA,ゆかりPARADISE３,I-02, I-02", "links": ["https://twitter.com/KimashiTowerP"]}, {"aliases": ["GYARISUTA!"], "pen_names": ["GYARI"], "position": "結月ゆかり、紲星あかり,ゆかりPARADISE３,J-13, J-13", "links": ["http://www.gyari.com/"]}, {"aliases": ["銀世界"], "pen_names": ["銀の太陽"], "position": "結月ゆかり×弦巻マキ,ゆかりPARADISE３,I-15, I-15", "links": ["https://www.pixiv.net/member.php?id=2089813"]}, {"aliases": ["黒白ぐれい"], "pen_names": ["黒白ぐれい"], "position": "結月ゆかり,ゆかりPARADISE３,J-18, J-18"}, {"aliases": ["コウノス"], "pen_names": ["村真砂"], "position": "結月ゆかり,ゆかりPARADISE３,H-23, H-23", "links": ["http://www.nicovideo.jp/user/46931224"]}, {"aliases": ["コンポラジュース"], "pen_names": ["こーりん"], "position": "結月ゆかり,ゆかりPARADISE３,J-07, J-07"}, {"aliases": ["【仮受付】サービス残業"], "pen_names": ["つなまよ"], "position": "結月ゆかり,ゆかりPARADISE３,J-09, J-09", "links": ["https://www.pixiv.net/member.php?id=29587396"]}, {"aliases": ["さかなや。"], "pen_names": ["うお"], "position": "結月ゆかり,ゆかりPARADISE３,H-20, H-20", "links": ["https://twitter.com/uo_Zkura"]}, {"aliases": ["桜華音"], "pen_names": ["来栖遥希"], "position": "結月ゆかり,ゆかりPARADISE３,H-08, H-08", "links": ["http://asagicafe.grupo.jp/"]}, {"aliases": ["SUNTRY"], "pen_names": ["<BOSS>"], "position": "結月ゆかり、弦巻マキ,ゆかりPARADISE３,I-17, I-17", "links": ["http://twitter.com/BOSS_CAU"]}, {"aliases": ["SEACLOUD"], "pen_names": ["荒居栂美"], "position": "結月ゆかり×東北きりたん,ゆかりPARADISE３,J-16, J-16", "links": ["https://www.pixiv.net/member.php?id=2464368"]}, {"aliases": ["Schenkel \n\tUnion"], "pen_names": ["羽山悠"], "position": "結月ゆかり,ゆかりPARADISE３,I-24, I-24", "links": ["https://www.pixiv.net/member.php?id=1928167"]}, {"aliases": ["cisco"], "pen_names": ["cisco"], "position": "結月ゆかり,ゆかりPARADISE３,H-04, H-04", "links": ["http://www.nicovideo.jp/mylist/57951420"]}, {"aliases": ["四辺工房"], "pen_names": ["しべ"], "position": "結月ゆかり、紲星あかり、（初音ミク）,ゆかりPARADISE３,H-22, H-22", "links": ["https://twitter.com/shibecraft"]}, {"aliases": ["シンセカイセット"], "pen_names": ["菖蒲"], "position": "結月ゆかり、東北きりたん、紲星あかり,ゆかりPARADISE３,I-06, I-06", "links": ["https://twitter.com/sho_bu_1116"]}, {"aliases": ["ZooAnime"], "pen_names": ["ズウアニメ"], "position": "結月ゆかり,ゆかりPARADISE３,J-12, J-12", "links": ["https://twitter.com/ZooAnime"]}, {"aliases": ["すみーず・みー"], "pen_names": ["お部屋片隅"], "position": "結月ゆかり,ゆかりPARADISE３,J-15, J-15", "links": ["https://twitter.com/katasumi5o"]}, {"aliases": ["ゼータクサーロイン"], "pen_names": ["senkei"], "position": "結月ゆかり,ゆかりPARADISE３,I-21, I-21", "links": ["https://twitter.com/senkei4862"]}, {"aliases": ["Salty Chocolat.*"], "pen_names": ["春野しょこら.*"], "position": "結月ゆかり,ゆかりPARADISE３,J-11, J-11", "links": ["https://twitter.com/chocopic_"]}, {"aliases": ["Soleil'Garden"], "pen_names": ["颯焦太"], "position": "結月ゆかり,ゆかりPARADISE３,I-19, I-19", "links": ["https://www.pixiv.net/member.php?id=23164709"]}, {"aliases": ["茶碗蒸し"], "pen_names": ["水無月"], "position": "結月ゆかり,ゆかりPARADISE３,J-08, J-08"}, {"aliases": ["月あかり街道"], "pen_names": ["鈴月詩希"], "position": "結月ゆかり、紲星あかり、ゆづきず,ゆかりPARADISE３,I-11, I-11"}, {"aliases": ["月明かりの桜"], "pen_names": ["桜華"], "position": "結月ゆかり×弦巻マキ,ゆかりPARADISE３,I-16, I-16", "links": ["https://twitter.com/sakuraka_night"]}, {"aliases": ["月見野番士"], "pen_names": ["椎奈そあら"], "position": "結月ゆかり,ゆかりPARADISE３,J-02, J-02"}, {"aliases": ["TFV藝研"], "pen_names": ["手布部"], "position": "京町セイカ×結月ゆかり、タカハシ,ゆかりPARADISE３,I-07, I-07", "links": ["https://www.pixiv.net/member.php?id=12815971"]}, {"aliases": ["天楼庵"], "pen_names": ["ギギ"], "position": "結月ゆかり,ゆかりPARADISE３,H-21, H-21", "links": ["https://10rouan.com/"]}, {"aliases": ["Dolphin \n\tRecord"], "pen_names": ["DolphinE"], "position": "結月ゆかり,ゆかりPARADISE３,H-05, H-05", "links": ["http://www.nicovideo.jp/mylist/60030233"]}, {"aliases": ["とんがー"], "pen_names": ["ししとー"], "position": "結月ゆかり、紲星あかり,ゆかりPARADISE３,I-10, I-10", "links": ["https://twitter.com/touga44"]}, {"aliases": ["夏色テルミット"], "pen_names": ["夏樹テル"], "position": "結月ゆかり,ゆかりPARADISE３,J-23, J-23", "links": ["https://www.pixiv.net/member.php?id=2613265"]}, {"aliases": ["のらくら劇場"], "pen_names": ["トロメラ"], "position": "結月ゆかり、紲星あかり,ゆかりPARADISE３,J-14, J-14", "links": ["https://twitter.com/toro_mera"]}, {"aliases": ["ハガネノウサギゴヤ"], "pen_names": ["ＫＡＩ"], "position": "結月ゆかり×IA、結月ゆかり、結月ゆかりの双子の弟、V flower,ゆかりPARADISE３,H-01,02, H-01,02", "links": ["https://ameblo.jp/heatmetalx/"]}, {"aliases": ["【仮受付】V-Resistanc"], "pen_names": ["ゆずのり"], "position": "ゆかいあ,ゆかりPARADISE３,I-03,04, I-03,04", "links": ["https://twitter.com/yukanoria"]}, {"aliases": ["窓際VAPER"], "pen_names": ["由紀乃"], "position": "結月ゆかり,ゆかりPARADISE３,I-22, I-22", "links": ["https://twitter.com/noir0776"]}, {"aliases": ["MIOTEC 2nd TEAM"], "pen_names": ["目から鱗"], "position": "結月ゆかり,ゆかりPARADISE３,H-13,14, H-13,14"}, {"aliases": ["Mireillemist"], "pen_names": ["らみえるみすと"], "position": "結月ゆかり,ゆかりPARADISE３,J-06, J-06", "links": ["https://twitter.com/ramielmist"]}, {"aliases": ["夢幻の世界"], "pen_names": ["B-ta"], "position": "結月ゆかり×紲星あかり,ゆかりPARADISE３,I-09, I-09", "links": ["https://www.pixiv.net/member.php?id=6997368"]}, {"aliases": ["メロン画紙"], "pen_names": ["儀水"], "position": "結月ゆかり×IA,ゆかりPARADISE３,J-22, J-22", "links": ["https://twitter.com/gisui_mizuki"]}, {"aliases": ["もじずり技術会"], "pen_names": ["Y.Yamashiro"], "position": "結月ゆかり、紲星あかり,ゆかりPARADISE３,H-12, H-12", "links": ["https://yukari.cafe/@shukukei/"]}, {"aliases": ["もちほっぺ"], "pen_names": ["トゥーミ"], "position": "結月ゆかり,ゆかりPARADISE３,J-19, J-19", "links": ["https://www.pixiv.net/member.php?id=1875134"]}, {"aliases": ["Monitor-P"], "pen_names": ["Monitor-P"], "position": "結月ゆかり,ゆかりPARADISE３,H-06, H-06", "links": ["http://www.nicovideo.jp/mylist/57098872"]}, {"aliases": ["焼き加減"], "pen_names": ["ミディアムレア"], "position": "結月ゆかり,ゆかりPARADISE３,J-03, J-03"}, {"aliases": ["やまなつらじお"], "pen_names": ["夏月りく"], "position": "結月ゆかり,ゆかりPARADISE３,J-01, J-01", "links": ["https://twitter.com/natuki_rik"]}, {"aliases": ["やるき66％"], "pen_names": ["たんぽぽ。"], "position": "結月ゆかり,ゆかりPARADISE３,H-17,18, H-17,18", "links": ["https://twitter.com/tanpopo8sky"]}, {"aliases": ["ゆかりの家"], "pen_names": ["Mr.kk"], "position": "結月ゆかり,ゆかりPARADISE３,J-21, J-21", "links": ["https://twitter.com/yukarinochi"]}, {"aliases": ["ゆづきずしーびー"], "pen_names": ["さかっち"], "position": "結月ゆかり×東北きりたん,ゆかりPARADISE３,I-05, I-05", "links": ["https://twitter.com/sakach15c"]}, {"aliases": ["妖怪パンダの自分勝手団"], "pen_names": ["ミサキえんじゅ"], "position": "結月ゆかり、弦巻マキ,ゆかりPARADISE３,I-14, I-14", "links": ["https://twitter.com/misakienjyu"]}, {"aliases": ["らーめんが見つかりません。"], "pen_names": ["黒猫かしす"], "position": "結月ゆかり、琴葉姉妹メイン,ゆかりPARADISE３,H-25, H-25"}, {"aliases": ["リトル本舗"], "pen_names": ["守木涼"], "position": "ゆかり・マキ・あかりで　ゆかりサンド！,ゆかりPARADISE３,I-13, I-13", "links": ["https://twitter.com/ryoumorigi"]}, {"aliases": ["LiLRAIN"], "pen_names": ["唯人"], "position": "結月ゆかり,ゆかりPARADISE３,H-03, H-03", "links": ["http://www.nicovideo.jp/watch/sm33084039"]}, {"aliases": ["LINK"], "pen_names": ["はてぃ〜"], "position": "結月ゆかり、IA,ゆかりPARADISE３,I-01, I-01", "links": ["http://www.nicovideo.jp/mylist/26128559"]}, {"aliases": ["Lv.1"], "pen_names": ["七森ぬぬ"], "position": "結月ゆかり,ゆかりPARADISE３,H-24, H-24", "links": ["http://twitter.com/with_out_sugar"]}, {"aliases": ["ロシアンブルー"], "pen_names": ["水夏"], "position": "結月ゆかり、琴葉姉妹,ゆかりPARADISE３,H-19, H-19", "links": ["https://twitter.com/ffql45z9"]}], "sources": [{"source": "Date: https://vocadb.net/E/1172/vocaloid-paradise-13", "type": ["Likely", "External"]}, {"source": "Participating circles: https://ttc.ninja-web.net/vo-para/vo-para10_list.htm", "type": ["Reliable", "Official"]}], "media": [{"path": "13_20211203064330_vo-para13.jpg", "sources": [{"source": "https://web.archive.org/web/20211203064330/http://ttc.ninja-web.net/vo-para/index.html", "type": ["Reliable", "Official"]}]}], "comments": "現在は４イベント混合のリストになっていますが、最終的には各イベントごとのリストに分けます。\n手続完了とは、「オンライン申込または申込書（郵送・直接受付）」「サークルカット」「サークル参加費」の３点を済ませた状態です。\n仮受付とは、上記のいずれかが済んでいない状態です。\n全ての手続が完了して7日経っても\n【仮受付】\nとなっている場合は、ボーパラ準備会までご連絡下さい。\nこの受付リストは、\n【仮受付】\nが外れることで、サークル参加手続完了のお知らせに代えさせていただきます。\n【仮受付】\n表示のサークルは手続完了となっていません。\n未完了の手続（サークルカット・サークル参加費のいずれか　または両方）を済ませるようにお願いします。\n申込後のスペース数変更（例：１スペース→２スペース）、サークルカットの差し替え、ペンネーム・メインキャラの変更は、最終締切までなら対応可能です。\nそれ以降では対応できない場合があります。\n変更申請等は\nこちら\nのメールフォームをご利用下さい。\n【8/4記載】\nこの度は、当イベントに多くのサークル参加申込ありがとうございました。\n延長締切を少し超えた申込含めて、仮受付含めて全当選となります。\nまた、前回・前々回同様に、AHSストア様の企業出展もございます。\nボーパラ13、ゆかパラ３、AHSパラ、カイミクパラでは、9/23のEofV（IAレボとかコトフェスとか）さん向け限定で、宅急便搬出の発払（元払）OKとしています（通常の宅配搬出は着払のみ対応）。\nこれで名古屋国際会議場→川口フレンディアへの直送が可能となります。\n【9/2記載】\n9/2にサークル参加案内を発送しました。\n9/8になっても到着しなかった場合は当準備会までご連絡下さい。\n【New!】\n館内図\n（PDFファイル）\nA-01〜A-24： \n\tカイミクPARADISE　（予備スペース：A-24）\nB-01〜D-40： VOCALOID PARADISE 13　（予備スペース：C-20・C-40・D-40）\nE-01〜G-16： AHS PARADISE　（予備スペース：E-08・G-08・）\nH-01〜J-24： ゆかりPARADISE３　（予備スペース：H-10・H-26・I-18・J-10）\n8/25　9:50更新"}